Metadata-Version: 2.4
Name: agent-framework-devui-visualizations
Version: 1.0.1b25121510
Summary: Debug UI for Microsoft Agent Framework with OpenAI-compatible API server with Visualizations.
Author-email: Maho Pacheco <mapach@microsoft.com>
Project-URL: homepage, https://github.com/mahomedalid/agent-framework
Project-URL: source, https://github.com/mahomedalid/agent-framework/tree/main/python
Project-URL: release_notes, https://github.com/mahomedalid/agent-framework/releases?q=tag%3Apython-1&expanded=true
Project-URL: issues, https://github.com/mahomedalid/agent-framework/issues
Classifier: License :: OSI Approved :: MIT License
Classifier: Development Status :: 4 - Beta
Classifier: Intended Audience :: Developers
Classifier: Programming Language :: Python :: 3
Classifier: Programming Language :: Python :: 3.10
Classifier: Programming Language :: Python :: 3.11
Classifier: Programming Language :: Python :: 3.12
Classifier: Programming Language :: Python :: 3.13
Classifier: Programming Language :: Python :: 3.14
Classifier: Typing :: Typed
Requires-Python: >=3.10
License-File: LICENSE
Requires-Dist: agent-framework-core
Requires-Dist: fastapi>=0.104.0
Requires-Dist: uvicorn[standard]>=0.24.0
Requires-Dist: python-dotenv>=1.0.0
Provides-Extra: dev
Requires-Dist: pytest>=7.0.0; extra == "dev"
Requires-Dist: watchdog>=3.0.0; extra == "dev"
Provides-Extra: all
Requires-Dist: pytest>=7.0.0; extra == "all"
Requires-Dist: watchdog>=3.0.0; extra == "all"
Dynamic: license-file
